Metadata-Version: 2.1
Name: cpdflib
Version: 9.3.1.2
Summary:  Python CFFI bindings for PDFlib.
Author: Florian Wagner
Author-email: florian@wagner-flo.net
Requires-Python: >=3.8
License-File: LICENSE
